dimcheck/__init__.py
dimcheck/custom.json
dimcheck/dimcheck_core.py
dimcheck/setting.json
dimcheck/si.json
src/__init__.py
src/dimcheck_core.py
dimcheck-1.0.2.dist-info/LICENSE
dimcheck-1.0.2.dist-info/METADATA
dimcheck-1.0.2.dist-info/WHEEL
dimcheck-1.0.2.dist-info/top_level.txt
dimcheck-1.0.2.dist-info/RECORD
