Metadata-Version: 2.1
Name: dimcheck
Version: 1.0.2
Summary: A physics dimension checker based on sympy
Home-page: https://github.com/Tony1527/dimcheck
Author: Tony Riddick
Author-email: tonyriddick1527@gmail.com
Keywords: physics,dimension,dimension analysis,unit checker,dimension checker,sympy,量纲分析,量纲检查,单位检查,量纲,单位,sympy
Classifier: Development Status :: 3 - Alpha
Classifier: Programming Language :: Python :: 3
Classifier: License :: OSI Approved :: Apache Software License
Classifier: Operating System :: OS Independent
Requires-Python: >=3.7
License-File: LICENSE
Requires-Dist: sympy
Requires-Dist: numpy
